ishelly/__init__.py
ishelly/api.py
ishelly/client.py
ishelly/components/base.py
ishelly/components/kvs.py
ishelly/components/schedule.py
ishelly/components/shelly.py
ishelly/components/switch.py
ishelly-0.1.5.2.dist-info/METADATA
ishelly-0.1.5.2.dist-info/WHEEL
ishelly-0.1.5.2.dist-info/RECORD
